<?xml version="1.0" encoding="utf-8"?>
<Entity parent="template_gaia_treasure">
  <Footprint>
    <Square width="0.5" depth="0.5"/>
    <Height>12.0</Height>
  </Footprint>
  <Identity>
    <SpecificName>Armor</SpecificName>
  </Identity>
  <Obstruction>
    <Static width="2.0" depth="2.0"/>
  </Obstruction>
  <Sound>
    <SoundGroups>
      <select>interface/select/resource/sel_metal.xml</select>
    </SoundGroups>
  </Sound>
  <Treasure>
    <Resources>
      <metal>40</metal>
      <wood>40</wood>
      <food>20</food>
    </Resources>
  </Treasure>
  <VisualActor>
    <Actor>units/trojans/loot</Actor>
  </VisualActor>
</Entity>
